{
	"name": "MascaraDePolir",
	"plugin-id": "Sprite",
	"sid": 839012424432385,
	"isGlobal": false,
	"instanceVariables": [],
	"behaviorTypes": [],
	"effectTypes": [],
	"animations": {
		"items": [
			{
				"frames": [
					{
						"width": 484,
						"height": 180,
						"originX": 0.5,
						"originY": 0.5,
						"originalSource": "",
						"exportFormat": "lossless",
						"exportQuality": 0.8,
						"imageSpriteId": 2580618,
						"collisionPoly": {
							"points": [
								0.7272727272727273,
								0.13333333333333333,
								0.8925619834710744,
								0.4222222222222222,
								0.9090909090909091,
								0.9111111111111111,
								0.18181818181818182,
								0.8222222222222222,
								0.10743801652892562,
								0.5555555555555556,
								0.09917355371900827,
								0.28888888888888886,
								0.15702479338842976,
								0.26666666666666666
							]
						},
						"useCollisionPoly": true,
						"duration": 1
					}
				],
				"sid": 810780625572696,
				"name": "Animation 1",
				"isLooping": false,
				"isPingPong": false,
				"repeatCount": 1,
				"repeatTo": 0,
				"speed": 5
			}
		],
		"subfolders": []
	}
}